signum/__init__.py
signum/core/__init__.py
signum/core/base_container.py
signum/core/containers.py
signum/core/freq_domain_signal.py
signum/core/time_domain_signal.py
signum/plotting/__init__.py
signum/plotting/bode_plotter.py
signum/plotting/iq_plotter.py
signum/plotting/nyquist_plotter.py
signum/plotting/plotter.py
signum/plotting/polar_plotter.py
signum/plotting/scaled_axes.py
signum/plotting/scaled_formatter.py
signum/tools/__init__.py
signum/tools/plotting_tools.py
signum/tools/scale_manager.py
signum-0.3.6.dist-info/METADATA
signum-0.3.6.dist-info/WHEEL
signum-0.3.6.dist-info/top_level.txt
signum-0.3.6.dist-info/RECORD
