Metadata-Version: 2.1
Name: signum
Version: 0.3.6
Summary: NumPy-based signal data container tools
Home-page: https://github.com/savetheginger/signum
Author: savetheginger
Author-email: mysh995@gmail.com
Requires-Python: >=3.7
Requires-Dist: numpy (>=1.16)
Requires-Dist: matplotlib
Provides-Extra: examples
Requires-Dist: notebook ; extra == 'examples'
